{
  "id": "qa-law-676",
  "type": "statute",
  "title": "قرار أميري رقم (1) لسنة 2004 باعتماد الحساب الختامي للدولة للسنة المالية 2001/ 2002",
  "short_name": "قرار أميري رقم (1) لسنة 2004 باعتماد الحساب الختامي للدولة للسنة المالية 2001/ 2002",
  "status": "in_force",
  "url": "https://www.almeezan.qa/LawPage.aspx?id=676&language=ar",
  "description": "Official Al Meezan listing metadata retained (LawViewWord fetching disabled by ingestion mode). Listed year: 2004.",
  "provisions": [],
  "definitions": []
}
