{
  "id": "qa-law-702",
  "type": "statute",
  "title": "قرار أميري رقم (24) لسنة 2003 بإعادة تشكيل مجلس إدارة المؤسسة العامة القطرية للكهرباء والماء",
  "short_name": "قرار أميري رقم (24) لسنة 2003 بإعادة تشكيل مجلس إدارة المؤسسة العامة القطرية للكهرباء والماء",
  "status": "in_force",
  "url": "https://www.almeezan.qa/LawViewWord.aspx?LawID=702&mode=DOC&language=ar",
  "description": "Official legislation text retrieved from Al Meezan LawViewWord Arabic source.",
  "provisions": [
    {
      "provision_ref": "art1",
      "section": "1",
      "title": "Article (1)",
      "content": "يعاد تشكيل مجلس إدارة الهيئة العامة القطرية للكهرباء والماء، على النحو التالي:\n1- سعادة السيد/عبد الله بن حمد العطية\nرئيساً\n2- السيد/عيسى شاهين الغانم\nنائباً للرئيس\n3- الدكتورة/لولوة عبد الله المسند\nعضواً\n4- الدكتور/أحمد حمد الحسن المهندي\nعضواً\n5- السيد/مفتاح جاسم مفتاح\nعضواً\n6- السيد/إبراهيم هاشم السادة\nعضواً\n7- المهندس/سعد شريدة الكعبي\nعضواً"
    },
    {
      "provision_ref": "art2",
      "section": "2",
      "title": "Article (2)",
      "content": "يلغى القرار الأميري رقم (35) لسنة 2000 المشار إليه."
    },
    {
      "provision_ref": "art3",
      "section": "3",
      "title": "Article (3)",
      "content": "على جميع الجهات المختصة، كل فيما يخصه، تنفيذ هذا القرار. ويُعمل به من تاريخ صدوره. وينشر في الجريدة الرسمية."
    }
  ],
  "definitions": []
}
