{
  "id": "qa-law-1117",
  "type": "statute",
  "title": "مرسوم رقم (40) لسنة 2003 بأيلولة ملكية الدولة لشركة قطر للحديد والصلب المحدودة «شركة مساهمة قطرية» إلى قطر للبترول",
  "short_name": "مرسوم رقم (40) لسنة 2003 بأيلولة ملكية الدولة لشركة قطر للحديد والصلب المحدودة «شركة مساهمة قطرية» إلى قطر للبترول",
  "status": "in_force",
  "url": "https://www.almeezan.qa/LawPage.aspx?id=1117&language=ar",
  "description": "Official Al Meezan listing metadata retained (LawViewWord fetching disabled by ingestion mode). Listed year: 2003.",
  "provisions": [],
  "definitions": []
}
