{
  "id": "qa-law-1176",
  "type": "statute",
  "title": "مرسوم رقم (51) لسنة 1982 بالتصديق على الاتفاقية الاقتصادية الموحدة بين دول مجلس التعاون لدول الخليج العربية",
  "short_name": "مرسوم رقم (51) لسنة 1982 بالتصديق على الاتفاقية الاقتصادية الموحدة بين دول مجلس التعاون لدول الخليج العربية",
  "status": "in_force",
  "url": "https://www.almeezan.qa/LawPage.aspx?id=1176&language=ar",
  "description": "Official Al Meezan listing metadata retained (LawViewWord fetching disabled by ingestion mode). Listed year: 1982.",
  "provisions": [],
  "definitions": []
}
