{
  "id": "qa-law-2035",
  "type": "statute",
  "title": "قرار وزير الشؤون البلدية والزراعة رقم (34) لسنة 2005م باعتبار مشروع «تطوير منطقة السد - المرحلة الثانية» من أعمال المنفعة العامة",
  "short_name": "قرار وزير الشؤون البلدية والزراعة رقم (34) لسنة 2005م باعتبار مشروع «تطوير منطقة السد - المرحلة الثانية» من أعمال الم...",
  "status": "in_force",
  "url": "https://www.almeezan.qa/LawPage.aspx?id=2035&language=ar",
  "description": "Official Al Meezan listing metadata retained (LawViewWord fetching disabled by ingestion mode). Listed year: 2005.",
  "provisions": [],
  "definitions": []
}
