{
  "id": "qa-law-2162",
  "type": "statute",
  "title": "قرار وزير الداخلية رقم (63) لسنة 2001 بتعديل قرار وزير الداخلية رقم (15) لسنة 1994 بشأن البدلات والعلاوات الإضافية والفنية التي تمنح لأعضاء قوة الشرطة",
  "short_name": "قرار وزير الداخلية رقم (63) لسنة 2001 بتعديل قرار وزير الداخلية رقم (15) لسنة 1994 بشأن البدلات والعلاوات الإضافية وا...",
  "status": "in_force",
  "url": "https://www.almeezan.qa/LawViewWord.aspx?LawID=2162&mode=DOC&language=ar",
  "description": "Official legislation text retrieved from Al Meezan LawViewWord Arabic source.",
  "provisions": [
    {
      "provision_ref": "art1",
      "section": "1",
      "title": "Article (1)",
      "content": "يُستبدل بالبند (45) من المجموعة الرابعة من قرار وزير الداخلية رقم (15) لسنة 1994 «علاوات فنية ومهنية» البند المرفق بهذا القرار."
    },
    {
      "provision_ref": "art2",
      "section": "2",
      "title": "Article (2)",
      "content": "يلغى كل حكم يخالف أحكام هذا القرار."
    },
    {
      "provision_ref": "art3",
      "section": "3",
      "title": "Article (3)",
      "content": "على جميع الجهات المختصة، كل فيما يخصه، تنفيذ هذا القرار. ويعمل به اعتباراً من تاريخ 1/4/2001، ويُنشر في الجريدة الرسمية."
    }
  ],
  "definitions": []
}
