{
  "id": "qa-law-2582",
  "type": "statute",
  "title": "قانون رقم (2) لسنة 2010 بتعديل بعض أحكام القانون رقم (4) لسنة 2008 بشأن إيجار العقارات",
  "short_name": "قانون رقم (2) لسنة 2010 بتعديل بعض أحكام القانون رقم (4) لسنة 2008 بشأن إيجار العقارات",
  "status": "in_force",
  "url": "https://www.almeezan.qa/LawViewWord.aspx?LawID=2582&mode=DOC&language=ar",
  "description": "Official legislation text retrieved from Al Meezan LawViewWord Arabic source.",
  "provisions": [
    {
      "provision_ref": "art1",
      "section": "1",
      "title": "Article (1)",
      "content": "يُستبدل بنص المادة ( 27 ) من القانون رقم (4) لسنة 2008 المشار إليه، النص التالي:"
    },
    {
      "provision_ref": "art27",
      "section": "27",
      "title": "Article (27)",
      "content": "«استثناءً من أحكام المادة ( 15 )، تمتد عقود إيجار الأماكن وأجزاء الأماكن المؤجرة لغير أغراض السكنى، الخاضعة لأحكام هذا القانون، والقائمة في 14/2/2010، وذلك لمدة سنة تبدأ من 15/2/2010، ما لم يتضمن العقد مدة أطول، أو رغب المستأجر في عدم التجديد، بشرط أن يكون المستأجر شاغلاً للعين المؤجرة.\nويجوز لمجلس الوزراء، بناء على اقتراح الوزير، ولدواعي المصلحة العامة، مد المدة المنصوص عليها في الفقرة السابقة لمدة أو مدد أخرى مماثلة، واستبعاد بعض عقود إيجار الأماكن وأجزاء الأماكن المؤجرة لغير أغراض السكنى من حكم الامتداد القانوني المشار إليه.»"
    },
    {
      "provision_ref": "art2",
      "section": "2",
      "title": "Article (2)",
      "content": "على جميع الجهات المختصة، كل فيما يخصه، تنفيذ هذا القانون. ويًعمل به من 15/2/2010. ويُنشر في الجريدة الرسمية."
    }
  ],
  "definitions": []
}
