{
  "id": "qa-law-3324",
  "type": "statute",
  "title": "قرار مجلس الوزراء رقم (37) لسنة 2006 بتعديل تنظيم بعض الوحدات الإدارية التي تتألف منها وزارة الأوقاف والشؤون الإسلامية",
  "short_name": "قرار مجلس الوزراء رقم (37) لسنة 2006 بتعديل تنظيم بعض الوحدات الإدارية التي تتألف منها وزارة الأوقاف والشؤون الإسلامية",
  "status": "in_force",
  "url": "https://www.almeezan.qa/LawViewWord.aspx?LawID=3324&mode=DOC&language=ar",
  "description": "Official legislation text retrieved from Al Meezan LawViewWord Arabic source.",
  "provisions": [
    {
      "provision_ref": "art1",
      "section": "1",
      "title": "Article (1)",
      "content": "ينقل إلى اختصاصات إدارة شؤون المساجد المنصوص عليها في المادة (13) من القانون رقم (9) لسنة 1993 المشار إليه، الاختصاص المنصوص عليه في البند (5) من المادة (10) على النحو التالي:\n«4- إقامة المساجد والترخيص بها حسب احتياجات المناطق المختلفة، والعمل على صيانتها وتأثيثها، والمحافظة عليها، ورعاية جميع شؤونها»."
    },
    {
      "provision_ref": "art2",
      "section": "2",
      "title": "Article (2)",
      "content": "على جميع الجهات المختصة، كل فيما يخصه، تنفيذ هذا القرار. ويعمل به من تاريخ صدوره. وينشر في الجريدة الرسمية."
    }
  ],
  "definitions": []
}
