{
  "id": "qa-law-3878",
  "type": "statute",
  "title": "قرار وزاري رقم (75) لسنة 2006 بشأن تحديد الرسوم المقررة على حق انتفاع غير القطريين بالعقارات والوحدات السكنية في المناطق الاستثمارية",
  "short_name": "قرار وزاري رقم (75) لسنة 2006 بشأن تحديد الرسوم المقررة على حق انتفاع غير القطريين بالعقارات والوحدات السكنية في المن...",
  "status": "in_force",
  "url": "https://www.almeezan.qa/LawPage.aspx?id=3878&language=ar",
  "description": "Official Al Meezan listing metadata retained (LawViewWord fetching disabled by ingestion mode). Listed year: 2006.",
  "provisions": [],
  "definitions": []
}
