{
  "id": "qa-law-3890",
  "type": "statute",
  "title": "قرار وزير شؤون الخدمة المدنية والإسكان رقم (7) لسنة 2006 بالموافقة على تسجيل وشهر الجمعية القطرية لمهندسي البترول",
  "short_name": "قرار وزير شؤون الخدمة المدنية والإسكان رقم (7) لسنة 2006 بالموافقة على تسجيل وشهر الجمعية القطرية لمهندسي البترول",
  "status": "in_force",
  "url": "https://www.almeezan.qa/LawPage.aspx?id=3890&language=ar",
  "description": "Official Al Meezan listing metadata retained (LawViewWord fetching disabled by ingestion mode). Listed year: 2006.",
  "provisions": [],
  "definitions": []
}
