{
  "id": "qa-law-3883",
  "type": "statute",
  "title": "قرار وزير العدل رقم (77) لسنة 2011 بإنشاء أقسام في الوحدات الإدارية التي يتألف منها مركز الدراسات القانونية والقضائية وتعيين اختصاصاتها",
  "short_name": "قرار وزير العدل رقم (77) لسنة 2011 بإنشاء أقسام في الوحدات الإدارية التي يتألف منها مركز الدراسات القانونية والقضائية...",
  "status": "in_force",
  "url": "https://www.almeezan.qa/LawPage.aspx?id=3883&language=ar",
  "description": "Official Al Meezan listing metadata retained (LawViewWord fetching disabled by ingestion mode). Listed year: 2011.",
  "provisions": [],
  "definitions": []
}
