{
  "id": "qa-law-4395",
  "type": "statute",
  "title": "مرسوم رقم (34) لسنة 2007 بشأن التعرفة الجمركية الموحدة",
  "short_name": "مرسوم رقم (34) لسنة 2007 بشأن التعرفة الجمركية الموحدة",
  "status": "in_force",
  "url": "https://www.almeezan.qa/LawViewWord.aspx?LawID=4395&mode=DOC&language=ar",
  "description": "Official legislation text retrieved from Al Meezan LawViewWord Arabic source.",
  "provisions": [
    {
      "provision_ref": "art1",
      "section": "1",
      "title": "Article (1)",
      "content": "يعمل بالتعرفة الجمركية الموحدة المرفقة بهذا المرسوم."
    },
    {
      "provision_ref": "art2",
      "section": "2",
      "title": "Article (2)",
      "content": "يلغى كل حكم يخالف أحكام هذا المرسوم."
    },
    {
      "provision_ref": "art3",
      "section": "3",
      "title": "Article (3)",
      "content": "على جميع الجهات المختصة، كل فيما يخصه، تنفيذ هذا المرسوم، ويُعمل به من الأول من يناير 2007. وينشر في الجريدة الرسمية."
    }
  ],
  "definitions": []
}
