{
  "id": "qa-law-4405",
  "type": "statute",
  "title": "قرار وزير الاقتصاد والتجارة رقم (158) لسنة 2007 بتحويل شركة مجمع شركات المناعي من شركة مساهمة خاصة إلى شركة مساهمة",
  "short_name": "قرار وزير الاقتصاد والتجارة رقم (158) لسنة 2007 بتحويل شركة مجمع شركات المناعي من شركة مساهمة خاصة إلى شركة مساهمة",
  "status": "in_force",
  "url": "https://www.almeezan.qa/LawPage.aspx?id=4405&language=ar",
  "description": "Official Al Meezan listing metadata retained (LawViewWord fetching disabled by ingestion mode). Listed year: 2007.",
  "provisions": [],
  "definitions": []
}
