{
  "id": "qa-law-4826",
  "type": "statute",
  "title": "مرسوم رقم (68) لسنة 2012 بالتصديق على اتفاقية الخدمات الجوية بين حكومة دولة قطر ومجلس وزراء جمهورية ألبانيا",
  "short_name": "مرسوم رقم (68) لسنة 2012 بالتصديق على اتفاقية الخدمات الجوية بين حكومة دولة قطر ومجلس وزراء جمهورية ألبانيا",
  "status": "in_force",
  "url": "https://www.almeezan.qa/LawViewWord.aspx?LawID=4826&mode=DOC&language=ar",
  "description": "Official legislation text retrieved from Al Meezan LawViewWord Arabic source.",
  "provisions": [
    {
      "provision_ref": "art1",
      "section": "1",
      "title": "Article (1)",
      "content": "صُودق على اتفاقية الخدمات الجوية بين حكومة دولة قطر ومجلس وزراء جمهورية ألبانيا، الموقعة بمدينة تيرانا بتاريخ 18/10/2011، المرفق نصها بهذا المرسوم، وتكون لها قوة القانون، وفقاً للمادة ( 68 ) من الدستور."
    },
    {
      "provision_ref": "art2",
      "section": "2",
      "title": "Article (2)",
      "content": "على جميع الجهات المختصة، كل فيما يخصه، تنفيذ هذا المرسوم. ويُعمل به من تاريخ صدوره. ويُنشر في الجريدة الرسمية."
    }
  ],
  "definitions": []
}
