{
  "id": "qa-law-4950",
  "type": "statute",
  "title": "قرار رقم (98) لسنة 2013 بتخويل صفة مأموري الضبط القضائي",
  "short_name": "قرار رقم (98) لسنة 2013 بتخويل صفة مأموري الضبط القضائي",
  "status": "in_force",
  "url": "https://www.almeezan.qa/LawViewWord.aspx?LawID=4950&mode=DOC&language=ar",
  "description": "Official legislation text retrieved from Al Meezan LawViewWord Arabic source.",
  "provisions": [
    {
      "provision_ref": "art1",
      "section": "1",
      "title": "Article (1)",
      "content": "يكون للسادة التالية اسماءهم صفة مأموري الضبط القضائي في إثبات الجرائم التي تقع بالمخالفة لأحكام القوانين المشار إليها والقرارات المنفذة لها:-\nم\nالاسم\nرقم البطاقة الشخصية\n1\nمحمود السيد ابراهيم رمضان\n----------------\n2\nمحمد احمد يوسف حسن السيد\n----------------\n3\nمصطفى محمد انور محمد\n----------------\n4\nبخيتة سالم محمد المري\n----------------\n5\nعاصم عبدالوهاب علي\n----------------\n6\nاحمد حلمي عبده شرف\n----------------\n7\nعائشة عثمان حسن اليوسف\n----------------\n8\nنوره فيصل جبر النعيمي\n----------------\n9\nمها علي عبداللطيف النعيمي\n----------------\n10\nاحمد عادل ابراهيم الباجوري\n----------------\n11\nمنيره محمد يوسف الدوسري\n----------------\n12\nميثاء سلطان ابراهيم الكواري\n----------------\n13\nابراهيم زياد هندي\n----------------\n14\nاحمد مطر جزاع الشمري\n----------------\n15\nالعنود مدلول تميم الدوسري\n----------------\n16\nمحمد صالح سالم عجيم\n----------------"
    },
    {
      "provision_ref": "art2",
      "section": "2",
      "title": "Article (2)",
      "content": "على جميع الجهات المُختصة كُلٍ فيما يخصه، تنفيذ هذا القرار، ويعمل به من تاريخ صدوره، ويُنشر في الجريدة الرسمية."
    }
  ],
  "definitions": []
}
