{
  "id": "qa-law-6089",
  "type": "statute",
  "title": "قرار وزير الشؤون البلدية والزراعة رقم (231) لسنة 2004م بتعيين الحدود الجغرافية لبلدية الظعاين",
  "short_name": "قرار وزير الشؤون البلدية والزراعة رقم (231) لسنة 2004م بتعيين الحدود الجغرافية لبلدية الظعاين",
  "status": "in_force",
  "url": "https://www.almeezan.qa/LawPage.aspx?id=6089&language=ar",
  "description": "Official Al Meezan listing metadata retained (LawViewWord fetching disabled by ingestion mode). Listed year: 2004.",
  "provisions": [],
  "definitions": []
}
