{
  "id": "qa-law-6692",
  "type": "statute",
  "title": "قرار رقم (100) لسنة 2015 بإلغاء الضبطية القضائية الممنوحة لبعض موظفي وزارة العمل والشؤون الاجتماعية",
  "short_name": "قرار رقم (100) لسنة 2015 بإلغاء الضبطية القضائية الممنوحة لبعض موظفي وزارة العمل والشؤون الاجتماعية",
  "status": "in_force",
  "url": "https://www.almeezan.qa/LawPage.aspx?id=6692&language=ar",
  "description": "Official Al Meezan listing metadata retained (LawViewWord fetching disabled by ingestion mode). Listed year: 2015.",
  "provisions": [],
  "definitions": []
}
