{
  "id": "qa-law-7452",
  "type": "statute",
  "title": "مرسوم رقم (79) لسنة 2017 بالتصديق على مذكرة تفاهم للتعاون في مجالي الشباب والرياضة بين حكومة دولة قطر وحكومة جمهورية أذربيجان",
  "short_name": "مرسوم رقم (79) لسنة 2017 بالتصديق على مذكرة تفاهم للتعاون في مجالي الشباب والرياضة بين حكومة دولة قطر وحكومة جمهورية...",
  "status": "in_force",
  "url": "https://www.almeezan.qa/LawViewWord.aspx?LawID=7452&mode=DOC&language=ar",
  "description": "Official legislation text retrieved from Al Meezan LawViewWord Arabic source.",
  "provisions": [
    {
      "provision_ref": "art1",
      "section": "1",
      "title": "Article (1)",
      "content": "صُودق على مذكرة تفاهم للتعاون في مجالي الشباب والرياضة بين حكومة دولة قطر وحكومة جمهورية أذربيجان، الموقعة بمدينة الدوحة بتاريخ 27/2/2017، المرفق نصها بهذا المرسوم، وتكون لها قوة القانون، وفقاً للمادة ( 68 ) من الدستور."
    },
    {
      "provision_ref": "art2",
      "section": "2",
      "title": "Article (2)",
      "content": "على جميع الجهات المختصة، كل فيما يخصه، تنفيذ هذا المرسوم. ويُعمل به من تاريخ صدوره. ويُنشر في الجريدة الرسمية."
    }
  ],
  "definitions": []
}
