{
  "id": "qa-law-7491",
  "type": "statute",
  "title": "قرار وزير الأوقاف والشؤون الإسلامية رقم (75) لسنة 2017 بتنظيم وتحديد بيانات سجل قيد مقاولي الحج والعمرة",
  "short_name": "قرار وزير الأوقاف والشؤون الإسلامية رقم (75) لسنة 2017 بتنظيم وتحديد بيانات سجل قيد مقاولي الحج والعمرة",
  "status": "in_force",
  "url": "https://www.almeezan.qa/LawPage.aspx?id=7491&language=ar",
  "description": "Official Al Meezan listing metadata retained (LawViewWord fetching disabled by ingestion mode). Listed year: 2017.",
  "provisions": [],
  "definitions": []
}
