{
  "id": "qa-law-7513",
  "type": "statute",
  "title": "قرار وزير الاقتصاد والتجارة رقم (433) لسنة 2017 بتعديل بعض أحكام القرار رقم (410) لسنة 2014 بتحديد رسوم الخدمات الخاصة بحماية حقوق الملكية الفكرية",
  "short_name": "قرار وزير الاقتصاد والتجارة رقم (433) لسنة 2017 بتعديل بعض أحكام القرار رقم (410) لسنة 2014 بتحديد رسوم الخدمات الخاص...",
  "status": "in_force",
  "url": "https://www.almeezan.qa/LawPage.aspx?id=7513&language=ar",
  "description": "Official Al Meezan listing metadata retained (LawViewWord fetching disabled by ingestion mode). Listed year: 2017.",
  "provisions": [],
  "definitions": []
}
