{
  "id": "qa-law-7893",
  "type": "statute",
  "title": "قرار وزير الاقتصاد والتجارة رقم (396) لسنة 2017 بشأن ضوابط وإجراءات الترخيص بفتح مكاتب تمثيل تجاري بالدولة",
  "short_name": "قرار وزير الاقتصاد والتجارة رقم (396) لسنة 2017 بشأن ضوابط وإجراءات الترخيص بفتح مكاتب تمثيل تجاري بالدولة",
  "status": "in_force",
  "url": "https://www.almeezan.qa/LawPage.aspx?id=7893&language=ar",
  "description": "Official Al Meezan listing metadata retained (LawViewWord fetching disabled by ingestion mode). Listed year: 2017.",
  "provisions": [],
  "definitions": []
}
