{
  "id": "qa-law-7966",
  "type": "statute",
  "title": "مرسوم رقم (14) لسنة 2019 بالتصديق على اتفاقية المساعدة الإدارية المتبادلة في المسائل الضريبية",
  "short_name": "مرسوم رقم (14) لسنة 2019 بالتصديق على اتفاقية المساعدة الإدارية المتبادلة في المسائل الضريبية",
  "status": "in_force",
  "url": "https://www.almeezan.qa/LawPage.aspx?id=7966&language=ar",
  "description": "Official Al Meezan listing metadata retained (LawViewWord fetching disabled by ingestion mode). Listed year: 2019.",
  "provisions": [],
  "definitions": []
}
