{
  "id": "qa-law-8187",
  "type": "statute",
  "title": "قرار رقم (180) لسنة 2019م بتخويل بعض موظفي وزارة التجارة والصناعة صفة مأموري الضبط القضائي",
  "short_name": "قرار رقم (180) لسنة 2019م بتخويل بعض موظفي وزارة التجارة والصناعة صفة مأموري الضبط القضائي",
  "status": "in_force",
  "url": "https://www.almeezan.qa/LawViewWord.aspx?LawID=8187&mode=DOC&language=ar",
  "description": "Official legislation text retrieved from Al Meezan LawViewWord Arabic source.",
  "provisions": [
    {
      "provision_ref": "art1",
      "section": "1",
      "title": "Article (1)",
      "content": "يكون لموظفي وزارة التجارة والصناعة التالية أسماؤهما صفة مأموري الضبط القضائي في ضبط وإثبات الجرائم التي تقع بالمُخالفة لأحكام القوانين ارقام 12 لسنة 1972 و 19 لسنة 2006 و 8 لسنة 2008 ، المُشار إليها والقرارات المُنفذه لها وهم:\nم\nالاسم\nالمسمى الوظيفي\n1\nعبدالرحمن جمعة سالم الهتمي\nمراقب أسواق رابع\n2\nراشد حمد راشد علي الاصم\nمراقب أسواق خامس\n3\nخليفة خالد خليفة المعاضيد\nمراقب أسواق رابع\n4\nحمد راشد سالم المري\nمراقب أسواق خامس\n5\nسالم ظاهر حويدر الشمري\nمراقب أسواق رابع\n6\nمنصور عبدالله عبدالرحمن محمد\nمراقب أسواق ثان\n7\nسالم حمد علي المري\nمراقب أسواق ثان\n8\nيوسف راشد ناصر المهندي\nمراقب أسواق ثالث\n9\nعبدالله خالد علي الخليفي\nمراقب أسواق رابع\n10\nعلي احمد علي السادة\nمراقب أسواق ثالث\n11\nعبدالرحمن عبدالله سعيد النملان\nمراقب أسواق رابع\n12\nمحمد علي حمد المري\nمراقب أسواق رابع\n13\nمنصور سعيد محمد الهاجري\nمفتش أسواق ثالث\n14\nحمد محمد حمد المري\nمراقب أسواق رابع\n15\nصالح حمد علي الكريبي المري\nمراقب أسواق رابع\n16\nدهام مفتاح دهام الخليفي\nمفتش أسواق ثاني\n17\nحمد جابر سعيد البريدي\nمراقب أسواق ثالث\n18\nيوسف عبدالله يوسف الجسيمان\nمراقب أسواق رابع\n19\nطلال الحاج فرج الأحمد\nمراقب أسواق رابع\n20\nسلطان خليفة علي السويدي\nمفتش أسواق ثالث\n21\nخالد ثاني فيروز عبدالله\nمراقب أسواق خامس\n22\nإبراهيم سعد هلال المهندي\nمراقب أسواق ثالث\n23\nمحمد محمود سطام الظاهر\nمراقب أسواق ثالث\n24\nسعد محمد علي الحمادي\nمفتش أسواق ثالث\n25\nإبراهيم مرزوق فرج المسلماني\nمراقب أسواق رابع\n26\nعبدالله حسين محمد الهيل\nمراقب أسواق رابع\n27\nاحمد علي محمد حميد\nمراقب أسواق رابع"
    },
    {
      "provision_ref": "art2",
      "section": "2",
      "title": "Article (2)",
      "content": "على جميع الجهات المُختصة كُلٍ فيما يَخُصه، تَنفيذ هذا القرار، ويُعمل بهِ من تاريخ صدوره، ويُنشر في الجريدة الرسمية."
    }
  ],
  "definitions": []
}
