{
  "id": "qa-law-8232",
  "type": "statute",
  "title": "قرار وزير العدل رقم (3) لسنة 2020 بتحديد مواصفات مقر مزاولة أعمال الوساطة العقارية",
  "short_name": "قرار وزير العدل رقم (3) لسنة 2020 بتحديد مواصفات مقر مزاولة أعمال الوساطة العقارية",
  "status": "in_force",
  "url": "https://www.almeezan.qa/LawViewWord.aspx?LawID=8232&mode=DOC&language=ar",
  "description": "Official legislation text retrieved from Al Meezan LawViewWord Arabic source.",
  "provisions": [
    {
      "provision_ref": "art1",
      "section": "1",
      "title": "Article (1)",
      "content": "يُشترط أن يتوفر في المقر الذي يتخذه الشخص الطبيعي مقراً لمزاولة أعمال الوساطة العقارية، المواصفات التالية:\n1- أن يكون ملائماً ومخصصاً لمزاولة أعمال الوساطة العقارية دون أي نشاط آخر لذات المرخص له أو لغيره.\n2- أن يكون مستوفياً لاشتراطات الأمن والسلامة والدفاع المدني.\n3- أن يكون مرخصاً به كمقر لمزاولة نشاط تجاري من وزارة التجارة والصناعة.\n4- أن يكون مزوداً بالتجهيزات اللازمة لاستقبال العملاء والحفاظ على سرية المعاملات.\n5- أن يكون مزوداً بالتجهيزات اللازمة لاستقبال العملاء من ذوي الإعاقة وكبار السن.\n6- أن تُثَبت على واجهته لوحة تعريفية باللغة العربية، على الأقل، مبيناً بها نوع النشاط، ورقم الترخيص الصادر بمزاولة أعمال الوساطة العقارية والبيانات الأخرى التي تحددها الإدارة المختصة بشؤون الوسطاء العقاريين بوزارة العدل.\n7- أن يكون مزوداً بأجهزة الحاسب الآلي وبرامج البحث العقاري الحديثة.\n8- أن يخصص به مكان آمن لحفظ سندات الملكية ومستندات العملاء وعقود الوساطة العقارية.\n9- أن يكون دائماً طوال مدة الترخيص بمزاولة أعمال الوساطة العقارية."
    },
    {
      "provision_ref": "art2",
      "section": "2",
      "title": "Article (2)",
      "content": "على جميع الجهات المختصة، كل فيما يخصه، تنفيذ هذا القرار. ويُعمل به من اليوم التالي لتاريخ نشره في الجريدة الرسمية."
    }
  ],
  "definitions": []
}
