{
  "id": "qa-law-8284",
  "type": "statute",
  "title": "قرار رقم (42) لسنة 2020م بإلغاء تخويل أحد موظفي وزارة التجارة والصناعة صفة مأموري الضبط القضائي",
  "short_name": "قرار رقم (42) لسنة 2020م بإلغاء تخويل أحد موظفي وزارة التجارة والصناعة صفة مأموري الضبط القضائي",
  "status": "in_force",
  "url": "https://www.almeezan.qa/LawPage.aspx?id=8284&language=ar",
  "description": "Official Al Meezan listing metadata retained (LawViewWord fetching disabled by ingestion mode). Listed year: 2020.",
  "provisions": [],
  "definitions": []
}
