{
  "id": "qa-law-8339",
  "type": "statute",
  "title": "قرار وزير البلدية والبيئة رقم (106) لسنة 2020 بتحديد البذور والتقاوي والشتلات السامة التي يمنع زراعتها ودخولها الى دولة قطر",
  "short_name": "قرار وزير البلدية والبيئة رقم (106) لسنة 2020 بتحديد البذور والتقاوي والشتلات السامة التي يمنع زراعتها ودخولها الى دو...",
  "status": "in_force",
  "url": "https://www.almeezan.qa/LawPage.aspx?id=8339&language=ar",
  "description": "Official Al Meezan listing metadata retained (LawViewWord fetching disabled by ingestion mode). Listed year: 2020.",
  "provisions": [],
  "definitions": []
}
