{
  "id": "qa-law-8475",
  "type": "statute",
  "title": "قرار وزاري رقم (262) لسنة 2020 بإعادة تسمية رئيس وأعضاء لجان فض المنازعات الإيجارية",
  "short_name": "قرار وزاري رقم (262) لسنة 2020 بإعادة تسمية رئيس وأعضاء لجان فض المنازعات الإيجارية",
  "status": "in_force",
  "url": "https://www.almeezan.qa/LawViewWord.aspx?LawID=8475&mode=DOC&language=ar",
  "description": "Official legislation text retrieved from Al Meezan LawViewWord Arabic source.",
  "provisions": [
    {
      "provision_ref": "art1",
      "section": "1",
      "title": "Article (1)",
      "content": "يُسمّى رئيس وأعضاء لجان فض المنازعات الإيجارية الخمسة على النحو التالي :\nاللجنة الأولى:\n1- القاضي/ محمد فضل زين القاضي رئيسًا\n2- السيد/ محمد حسن حمد النعيمي عضوًا\n3- السيد/ خليفة علي صالح المهندي عضوًا\nاللجنة الثانية :\n1- القاضي/ غانم راشد مبارك الخيارين رئيسًا\n2- السيد/ عبدالعزيز عبدالله المنصوري عضوًا\n3- السيد / علي ظافر محمد القحطاني عضوًا\nاللجنة الثالثة:\n1- القاضي/ حمد صالح طالب النابت رئيسًا\n2- السيد / عتيق نوبي زايد الخليفي عضوًا\n3- السيد / سلطان وسام سلطان الهاجري عضوًا\nاللجنة الرابعة :\n1- القاضي/ محمد حسن جاسم الهيل رئيسًا\n2- السيد/ فيصل عثمان أحمد باوزير عضوًا\n3- السيد / سالم علي محمد الفهيدي المري عضوًا\nاللجنة الخامسة :\n1- القاضي/ سالم محمد حميد الشهواني رئيسًا\n2- السيد / سعد عبد الكريم القحطاني عضوًا\n3- السيد/ فهد هلال محمد علي المهندي عضوًا"
    },
    {
      "provision_ref": "art2",
      "section": "2",
      "title": "Article (2)",
      "content": "يُلغى كل حكم يخالف أحكام هذا القرار ."
    },
    {
      "provision_ref": "art3",
      "section": "3",
      "title": "Article (3)",
      "content": "على جميع الجهات المختصة ، كل فيما يخصه ، تنفيذ هذا القرار، ويُعمل به من تاريخ 1/ 10/ 2020، ويُنشر في الجريدة الرسمية ."
    }
  ],
  "definitions": []
}
