{
  "id": "qa-law-8774",
  "type": "statute",
  "title": "قرار وزير المالية رقم (20) لسنة 2021 بتطبيق متطلبات النشاط الجوهري على الأنشطة الاقتصادية التي تمارس في دولة قطر",
  "short_name": "قرار وزير المالية رقم (20) لسنة 2021 بتطبيق متطلبات النشاط الجوهري على الأنشطة الاقتصادية التي تمارس في دولة قطر",
  "status": "in_force",
  "url": "https://www.almeezan.qa/LawPage.aspx?id=8774&language=ar",
  "description": "Official Al Meezan listing metadata retained (LawViewWord fetching disabled by ingestion mode). Listed year: 2021.",
  "provisions": [],
  "definitions": []
}
