{
  "id": "qa-law-8885",
  "type": "statute",
  "title": "قرار رئيس مجلس الوزراء رقم (7) لسنة 2022 بتعيين منسق للشؤون الأمنية بمكتب رئيس مجلس الوزراء",
  "short_name": "قرار رئيس مجلس الوزراء رقم (7) لسنة 2022 بتعيين منسق للشؤون الأمنية بمكتب رئيس مجلس الوزراء",
  "status": "in_force",
  "url": "https://www.almeezan.qa/LawPage.aspx?id=8885&language=ar",
  "description": "Official Al Meezan listing metadata retained (LawViewWord fetching disabled by ingestion mode). Listed year: 2022.",
  "provisions": [],
  "definitions": []
}
