{
  "id": "qa-law-9127",
  "type": "statute",
  "title": "قرار وزير الثقافة رقم (7) لسنة 2023م باعتماد النظام الأساسي للمركز القطري الثقافي للمكفوفين",
  "short_name": "قرار وزير الثقافة رقم (7) لسنة 2023م باعتماد النظام الأساسي للمركز القطري الثقافي للمكفوفين",
  "status": "in_force",
  "url": "https://www.almeezan.qa/LawPage.aspx?id=9127&language=ar",
  "description": "Official Al Meezan listing metadata retained (LawViewWord fetching disabled by ingestion mode). Listed year: 2023.",
  "provisions": [],
  "definitions": []
}
