{
  "id": "qa-law-9737",
  "type": "statute",
  "title": "مرسوم رقم (65) لسنة 2024 بالتصديق على مذكرة تفاهم للتعاون في مجال التعليم والتعليم العالي والبحث العلمي بين حكومة دولة قطر وحكومة جمهورية بنغلاديش الشعبية",
  "short_name": "مرسوم رقم (65) لسنة 2024 بالتصديق على مذكرة تفاهم للتعاون في مجال التعليم والتعليم العالي والبحث العلمي بين حكومة دول...",
  "status": "in_force",
  "url": "https://www.almeezan.qa/LawPage.aspx?id=9737&language=ar",
  "description": "Official Al Meezan listing metadata retained (LawViewWord fetching disabled by ingestion mode). Listed year: 2024.",
  "provisions": [],
  "definitions": []
}
