{
  "id": "qa-law-9767",
  "type": "statute",
  "title": "مرسوم رقم (90) لسنة 2024 بالتصديق على مذكرة تفاهم بشأن إجراء المشاورات الـسـيـاسـيـة حـول الـقـضــايــا ذات الاهتمام المشترك بين وزارة الـخـارجـيـة بدولة قطر ووزارة الخارجية والأعمال الدولية والتجارة والطاقة بالكومنولث دومينيکا",
  "short_name": "مرسوم رقم (90) لسنة 2024 بالتصديق على مذكرة تفاهم بشأن إجراء المشاورات الـسـيـاسـيـة حـول الـقـضــايــا ذات الاهتمام...",
  "status": "in_force",
  "url": "https://www.almeezan.qa/LawViewWord.aspx?LawID=9767&mode=DOC&language=ar",
  "description": "Official legislation text retrieved from Al Meezan LawViewWord Arabic source.",
  "provisions": [
    {
      "provision_ref": "art1",
      "section": "1",
      "title": "Article (1)",
      "content": "صُودق على مذكرة تفاهم بشأن إجراء المشاورات السياسية حول القضايا ذات الاهتمام المشترك بين وزارة الخارجية بدولة قطر ووزارة الخارجية والأعمال الدولية والتجارة والطاقة بالكومنولث دومينيكا ، الموقعة بمدينة روسو بتاريخ 024/05/22 الـمـرفـق نـصـهـا بـهـذا المرسوم، وتكون لها قوة القانون ، وفقاً للمادة (68) من الدستور ."
    },
    {
      "provision_ref": "art2",
      "section": "2",
      "title": "Article (2)",
      "content": "على جميع الجهات المختصة، كل فيما يخصه، تنفيذ هذا المرسوم . ويُـعـمـل به من تاريخ صدوره. ويُنشر في الجريدة الرسمية."
    }
  ],
  "definitions": []
}
